caluma/__init__.py
caluma/caluma_analytics/README.md
caluma/caluma_analytics/__init__.py
caluma/caluma_analytics/apps.py
caluma/caluma_analytics/conftest.py
caluma/caluma_analytics/factories.py
caluma/caluma_analytics/filters.py
caluma/caluma_analytics/management/commands/run_analytics.py
caluma/caluma_analytics/migrations/0001_initial.py
caluma/caluma_analytics/migrations/0002_analytics_pivot_table.py
caluma/caluma_analytics/migrations/0003_starting_objects.py
caluma/caluma_analytics/migrations/0004_simple_history.py
caluma/caluma_analytics/migrations/0005_analytics_field_ordering.py
caluma/caluma_analytics/migrations/0006_rename_form_slug_fields.py
caluma/caluma_analytics/migrations/0007_add_analytics_description_field.py
caluma/caluma_analytics/migrations/0008_uuid_v7.py
caluma/caluma_analytics/migrations/__init__.py
caluma/caluma_analytics/models.py
caluma/caluma_analytics/pivot_table.py
caluma/caluma_analytics/schema.py
caluma/caluma_analytics/serializers.py
caluma/caluma_analytics/simple_table.py
caluma/caluma_analytics/sql.py
caluma/caluma_analytics/visibility.py
caluma/caluma_core/__init__.py
caluma/caluma_core/apps.py
caluma/caluma_core/collections.py
caluma/caluma_core/conftest.py
caluma/caluma_core/events.py
caluma/caluma_core/exceptions.py
caluma/caluma_core/factories.py
caluma/caluma_core/faker.py
caluma/caluma_core/filters.py
caluma/caluma_core/forms.py
caluma/caluma_core/health_checks.py
caluma/caluma_core/jexl.py
caluma/caluma_core/management/__init__.py
caluma/caluma_core/management/commands/__init__.py
caluma/caluma_core/management/commands/cleanup_history.py
caluma/caluma_core/management/commands/dump_caluma_config.py
caluma/caluma_core/management/commands/migrate.py
caluma/caluma_core/management/commands/migrate_to_prefixed_apps.py
caluma/caluma_core/models.py
caluma/caluma_core/mutation.py
caluma/caluma_core/ordering.py
caluma/caluma_core/pagination.py
caluma/caluma_core/permissions.py
caluma/caluma_core/relay.py
caluma-12.3.0.dist-info/METADATA
caluma-12.3.0.dist-info/WHEEL
caluma-12.3.0.dist-info/licenses/LICENSE
caluma-12.3.0.dist-info/licenses/LICENSES/CC-BY-4.0.md
caluma-12.3.0.dist-info/licenses/LICENSES/CC0-1.0.txt
caluma-12.3.0.dist-info/licenses/LICENSES/GFDL-1.3-or-later.txt
caluma-12.3.0.dist-info/licenses/LICENSES/GPL-3.0-or-later.txt
caluma-12.3.0.dist-info/RECORD
