Metadata-Version: 2.4
Name: caluma
Version: 12.3.0
Summary: Caluma Service providing GraphQL API
License: GPL-3.0-or-later
License-File: LICENSE
License-File: LICENSES/CC-BY-4.0.md
License-File: LICENSES/CC0-1.0.txt
License-File: LICENSES/GFDL-1.3-or-later.txt
License-File: LICENSES/GPL-3.0-or-later.txt
Author: Caluma
Author-email: info@caluma.io
Requires-Python: >=3.12,<4
Classifier: Development Status :: 5 - Production/Stable
Classifier: Intended Audience :: Developers
Classifier: License :: OSI Approved :: GNU General Public License v3 or later (GPLv3+)
Classifier: Programming Language :: Python :: 3
Classifier: Programming Language :: Python :: 3.12
Classifier: Programming Language :: Python :: 3.13
Classifier: Programming Language :: Python :: 3.14
Classifier: Programming Language :: Python :: 3.8
Requires-Dist: Django (>=4.2,<5.3)
Requires-Dist: dateparser (>=1.2.1,<2.0.0)
Requires-Dist: django-cors-headers (>=4.7.0,<5.0.0)
Requires-Dist: django-environ (>=0.12.0,<0.13.0)
Requires-Dist: django-filter (>=23.5,<26.0)
Requires-Dist: django-localized-fields (>=6.7,<7.0)
Requires-Dist: django-postgres-extra (>=2.0.8,<3.0.0)
Requires-Dist: django-simple-history (>=3.8.0,<4.0.0)
Requires-Dist: django-watchman (>=1.3.0,<2.0.0)
Requires-Dist: djangorestframework (>=3.15.2,<4.0.0)
Requires-Dist: graphene (>=3.4.3,<4.0.0)
Requires-Dist: graphene-django (>=3.2.2,<4.0.0)
Requires-Dist: graphql-core (>=3.2.6,<4.0.0)
Requires-Dist: graphql-relay (>=3.2.0,<4.0.0)
Requires-Dist: gunicorn (>=23.0.0,<25)
Requires-Dist: idna (>=3.10,<4.0)
Requires-Dist: minio (>=7.2.20,<8.0.0)
Requires-Dist: psycopg-binary (>=3.2.4,<4.0.0)
Requires-Dist: psycopg[binary] (>=3.2.4,<4.0.0)
Requires-Dist: pyjexl (>=0.3.0,<0.4.0)
Requires-Dist: python-memcached (>=1.62,<2.0)
Requires-Dist: requests (>=2.32.3,<3.0.0)
Requires-Dist: urllib3 (>=1.26.8,<3.0.0)
Requires-Dist: uuid7 (>=0.1.0,<0.2.0)
Project-URL: Documentation, https://caluma.gitbook.io/
Project-URL: Homepage, https://caluma.io
Project-URL: Repository, https://github.com/projectcaluma/caluma
